devour/__init__.py
devour/consumers.py
devour/exceptions.py
devour/handlers.py
devour/producers.py
devour/proxies.py
devour/schemas.py
devour/validators.py
devour/bin/__init__.py
devour/bin/devour_commands.py
devour/django/__init__.py
devour/django/apps.py
devour/django/common.py
devour/django/models.py
devour/django/receivers.py
devour/django/schemas.py
devour/django/management/__init__.py
devour/django/management/commands/__init__.py
devour/django/management/commands/consume.py
devour/django/utils/__init__.py
devour/django/utils/helpers.py
devour/utils/__init__.py
devour/utils/helpers.py
devour/utils/loaders.py
devour-0.6.3.dist-info/DESCRIPTION.rst
devour-0.6.3.dist-info/METADATA
devour-0.6.3.dist-info/RECORD
devour-0.6.3.dist-info/WHEEL
devour-0.6.3.dist-info/entry_points.txt
devour-0.6.3.dist-info/metadata.json
devour-0.6.3.dist-info/top_level.txt
