Metadata-Version: 2.0
Name: devour
Version: 0.6.3
Summary: UNKNOWN
Home-page: UNKNOWN
Author: http://github.com/brandoshmando
Author-email: brancraft@gmail.com
License: MIT
Keywords: kafka,django,pykafka,python,devour
Platform: UNKNOWN
Requires-Dist: pykafka
